[
	{
		"Referrals":[
			{"id":1,"name":"John Butler","referred_for":"UI/UX Designer","referred_by":"Steve Chris","time":"12 mins","status":"Pending"},
			{"id":2,"name":"Daniel","referred_for":"Salesforce Architect","referred_by":"Julia Lawson","time":"25 mins","status":"Applied"}
		],
		"Hires":[

		],
		"Connections":[
			{"id":1,"name":"Mary L","designation":"Sr. Software Engineer","referral_made":80},
			{"id":2,"name":"Julia Lawson","designation":"Sr. Human Resource Manager","referral_made":76},
			{"id":3,"name":"Chris","designation":"Sr. Software Engineer","referral_made":70},
			{"id":4,"name":"Stuart","designation":"UI Manager","referral_made":62},
			{"id":5,"name":"Steve Chris","designation":"Resource Manager","referral_made":56},
			{"id":6,"name":"Steven","designation":"Sr. Software Engineer","referral_made":50}
		],
		"invited":[
			{"id":1,"name":"Mary L","designation":"Sr. Software Engineering","referrals":3,"applied":3,"self":"public/images/Ui_Faces/Mary L.jpg"},
			{"id":2,"name":"Julia Lawson","designation":"Sr. Human Resource Manager","referrals":3,"applied":1,"self":"public/images/Ui_Faces/Julia Lawson.jpg"},
			{"id":3,"name":"Chris","designation":"Sr. Software Engineering","referrals":3,"applied":1,"self":"public/images/Ui_Faces/Chris.jpg"},
			{"id":4,"name":"Stuart","designation":"UI Manager","referrals":3,"applied":1,"self":"public/images/Ui_Faces/Christopher.jpg"},
			{"id":5,"name":"Steven","designation":"Sr. Software Engineering","referrals":3,"applied":1,"self":"public/images/Ui_Faces/Daniel.jpg"},
			{"id":6,"name":"Johnson","designation":"UI/UX Designer","referrals":3,"applied":1,"self":"public/images/Ui_Faces/Johnson.jpg"},
			{"id":7,"name":"John Butler","designation":"UI/UX Designer","referrals":3,"applied":1,"self":"public/images/Ui_Faces/John Butler.jpg"},
			{"id":8,"name":"Will Mark","designation":"iOS Developer","referrals":3,"applied":1,"self":"public/images/Ui_Faces/Willmark.jpg"}

		],
		"referred":[
			{"id":1,"name":"Christopher","referred_by":"Steve Chris","designation":"Sr. Software Engineer","ref_designation":"Resource Manager","status":"Pending","time":"12 mins ago","rewarded":"5.00"},
			{"id":2,"name":"Philippe","referred_by":"Julia Lawson","designation":"Sr. Software Engineer","ref_designation":"Sr. Human Resource Manager","status":"Accepted","time":"20 mins ago","rewarded":"5.00"},
			{"id":3,"name":"Kevin","referred_by":"Kristene Scot","designation":"Sr. Software Engineer","ref_designation":"Sr. Software Engineer","status":"Accepted","time":"20 hr ago","rewarded":"5.00"},
			{"id":4,"name":"Todd Linkon","referred_by":"Christopher","designation":"Sr. Software Engineer","ref_designation":"Sr. Software Engineer","status":"Pending","time":"26 May 2016","rewarded":"5.00"},
			{"id":5,"name":"George","referred_by":"Julia Lawson","designation":"Sr. Software Engineer","ref_designation":"Sr. Human Resource Manager","status":"Accepted","time":"25 May 2016","rewarded":"5.00"},
			{"id":6,"name":"Kristin","referred_by":"Will Mark","designation":"UI Manager","ref_designation":"iOS Developer","status":"Accepted","time":"25 May 2016","rewarded":"5.00"},
			{"id":7,"name":"Armen Hodge","referred_by":"John Butler","designation":"Sr. Software Engineer","ref_designation":"UI/UX Designer","status":"Accepted","time":"20 May 2016","rewarded":"5.00"},
			{"id":8,"name":"Watson","referred_by":"Steve Chris","designation":"UI/UX Designer","ref_designation":"UI/UX Designer","status":"Accepted","time":"20 May 2016","rewarded":"5.00"},
			{"id":9,"name":"Aryan Todd","referred_by":"Kristene Scot","designation":"Sr. Software Engineer","ref_designation":"Sr. Software Engineer","status":"Declined","time":"19 May 2016","rewarded":"5.00"}
		],
		"accepted":[
			{"id":"1","name":"Philippe","designation":"Sr. Software Engineer","status":"accepted","self":"public/images/Ui_Faces/Philippe.jpg"},
			{"id":"2","name":"Kevin","designation":"Sr. Human Resource Manager","status":"interviewed","self":"public/images/Ui_Faces/Kevin.jpg"},
			{"id":"3","name":"George","designation":"Sr. Software Engineer","status":"interviewed","self":"public/images/Ui_Faces/George.jpg"},
			{"id":"4","name":"Kristin","designation":"UI Manager","status":"hired","self":"public/images/Ui_Faces/Kristin.jpg"},
			{"id":"5","name":"Armen Hodge","designation":"Sr. Software Engineer","status":"offerMade","self":"public/images/Ui_Faces/Armen Hodge.jpg"},
			{"id":"6","name":"Watson","designation":"UI/UX Designer","status":"accepted","self":"public/images/Ui_Faces/Watson.jpg"}
		],
		"rewarded":[
			{"id":1,"name":"Mary L","designation":"Sr. Software Engineer","referred_to":"Chris","ref_designation":"Sr. Software Engineer","time":"12 mins ago","rewarded":"5.00"},
			{"id":1,"name":"Julia Lawson","designation":"Sr. Human Resource Manager","referred_to":"Johnson","ref_designation":"UI/UX Designer","time":"1 hr ago","rewarded":"5.00"},
			{"id":1,"name":"Chris","designation":"Sr. Software Engineer","referred_to":"John Butler","ref_designation":"UI/UX Designer","time":"1 day ago","rewarded":"5.00"},
			{"id":1,"name":"Christopher","designation":"UI Manager","referred_to":"Mary L","ref_designation":"Sr. Software Engineer","time":"2 days ago","rewarded":"5.00"},
			{"id":1,"name":"Daniel","designation":"Sr. Software Engineer","referred_to":"Will Mark","ref_designation":"iOS Developer","time":"5 days ago","rewarded":"5.00"},
			{"id":1,"name":"Johnson","designation":"UI/UX Designer","referred_to":"Julia Lawson","ref_designation":"Sr. Human Resource Manager","time":"5 days ago","rewarded":"5.00"},
			{"id":1,"name":"John Butler","designation":"UI/UX Designer","referred_to":"Daniel","ref_designation":"Sr. Software Engineer","time":"5 days ago","rewarded":"5.00"},
			{"id":1,"name":"Will Mark","designation":"iOS Developer","referred_to":"Christopher","ref_designation":"UI Manager","time":"6 days ago","rewarded":"5.00"}
		]

	}




]